pygame_phyics/__init__.py
pygame_phyics/collison.py
pygame_phyics/effect.py
pygame_phyics/error.py
pygame_phyics/event.py
pygame_phyics/game.py
pygame_phyics/input.py
pygame_phyics/instantiate.py
pygame_phyics/location.py
pygame_phyics/manger.py
pygame_phyics/mouse.py
pygame_phyics/save.py
pygame_phyics/scene.py
pygame_phyics/sheet.py
pygame_phyics/timertask.py
pygame_phyics/util.py
pygame_phyics/objects/__init__.py
pygame_phyics/objects/camera.py
pygame_phyics/objects/component.py
pygame_phyics/objects/gameobject.py
pygame_phyics/objects/joint.py
pygame_phyics/objects/object.py
pygame_phyics/objects/parent.py
pygame_phyics/objects/physics.py
pygame_phyics/objects/tilemap.py
pygame_phyics/objects/ui/__init__.py
pygame_phyics/objects/ui/button.py
pygame_phyics/objects/ui/inputfield.py
pygame_phyics/objects/ui/inputline.py
pygame_phyics/objects/ui/text.py
pygame_phyics/objects/ui/ui.py
pygame_phyics-1.2.2.dist-info/METADATA
pygame_phyics-1.2.2.dist-info/WHEEL
pygame_phyics-1.2.2.dist-info/top_level.txt
pygame_phyics-1.2.2.dist-info/RECORD
