Metadata-Version: 2.1
Name: pygame_phyics
Version: 1.2.2
Home-page: https://github.com/fireing123/pygame_phyics
Author: fireing123
Author-email: gimd82368@gmail.com
Requires-Dist: pygame
Requires-Dist: box2d
Requires-Dist: box2d-py
